{
	"configurations" : 
	[
		{
			"directories" : 
			[
				{
					"build" : ".",
					"jsonFile" : "directory-.-Debug-d0094a50bb2071803777.json",
					"minimumCMakeVersion" : 
					{
						"string" : "3.27"
					},
					"projectIndex" : 0,
					"source" : ".",
					"targetIndexes" : 
					[
						0
					]
				}
			],
			"name" : "Debug",
			"projects" : 
			[
				{
					"directoryIndexes" : 
					[
						0
					],
					"name" : "vaja2_algoritmi",
					"targetIndexes" : 
					[
						0
					]
				}
			],
			"targets" : 
			[
				{
					"directoryIndex" : 0,
					"id" : "Vaja2_algoritmi::@6890427a1f51a3e7e1df",
					"jsonFile" : "target-Vaja2_algoritmi-Debug-0adc860f9c65768f37df.json",
					"name" : "Vaja2_algoritmi",
					"projectIndex" : 0
				}
			]
		}
	],
	"kind" : "codemodel",
	"paths" : 
	{
		"build" : "C:/Users/pavel/CLionProjects/vaja2_algoritmi/cmake-build-debug",
		"source" : "C:/Users/pavel/CLionProjects/vaja2_algoritmi"
	},
	"version" : 
	{
		"major" : 2,
		"minor" : 6
	}
}
